ioligo/__init__.py
ioligo/oligo.py
ioligo-0.0.1.data/scripts/ioligo
ioligo-0.0.1.dist-info/LICENSE
ioligo-0.0.1.dist-info/METADATA
ioligo-0.0.1.dist-info/WHEEL
ioligo-0.0.1.dist-info/top_level.txt
ioligo-0.0.1.dist-info/RECORD
